masslos/__init__.py
masslos/distance.py
masslos/measure.py
masslos/py.typed
masslos/speed.py
masslos/unit.py
masslos/weight.py
masslos-0.2.3.dist-info/METADATA
masslos-0.2.3.dist-info/WHEEL
masslos-0.2.3.dist-info/licenses/LICENSE
masslos-0.2.3.dist-info/RECORD
